attrmap/__init__.py
attrmap/attrmap.py
attrmap/utils.py
attrmap-0.0.7.dist-info/LICENSE
attrmap-0.0.7.dist-info/METADATA
attrmap-0.0.7.dist-info/WHEEL
attrmap-0.0.7.dist-info/top_level.txt
attrmap-0.0.7.dist-info/RECORD
