Metadata-Version: 2.1
Name: attrmap
Version: 0.0.7
Summary: An open source tool with **read-only protection** to help users get rid of dictionary in Python.
Home-page: https://github.com/yiqunchen1999/attrmap
Author: Yiqun Chen
Author-email: yiqunchen1999@gmail.com
License: Apache Software License
Classifier: Programming Language :: Python :: 3.6
Classifier: Programming Language :: Python :: 3.7
Classifier: Programming Language :: Python :: 3.8
Classifier: Programming Language :: Python :: 3.9
Classifier: Programming Language :: Python :: 3.10
Classifier: License :: OSI Approved :: Apache Software License
Classifier: Operating System :: OS Independent
Requires-Python: >=3.6
License-File: LICENSE
Requires-Dist: pyyaml
Provides-Extra: pdf
Requires-Dist: ReportLab (>=1.2) ; extra == 'pdf'
Provides-Extra: rest
Requires-Dist: docutils (>=0.3) ; extra == 'rest'
